{
  "paper_id": "d1f64b08e5e91fb86617a4250329f24c1b70ea7a",
  "metadata": {
    "title": "THE RODENT PARVOVIRUSES",
    "coda_data_split": "train",
    "coda_paper_id": 3486,
    "coda_has_expert_labels": false,
    "subset": "custom_license"
  },
  "abstract": [
    {
      "original_text": "The parvoviruses are a large family of physically similar viruses infecting animals as diverse as man and moth (1,2).",
      "sentences": [
        [
          {
            "segment_text": "The parvoviruses are a large family of physically similar viruses infecting animals as diverse as man and moth ( 1,2 ) .",
            "crowd_label": "background"
          }
        ]
      ]
    },
    {
      "original_text": "Those which naturally infect vertebrates are divided into two subgroups, the adeno-associated viruses (AAV) and the autonomous parvoviruses.",
      "sentences": [
        [
          {
            "segment_text": "Those which naturally infect vertebrates are divided into two subgroups ,",
            "crowd_label": "background"
          },
          {
            "segment_text": "the adeno-associated viruses ( AAV ) and the autonomous parvoviruses .",
            "crowd_label": "background"
          }
        ]
      ]
    },
    {
      "original_text": "Members of the AAV subgroup, now also known as the Dependoviruses, are totally dependent upon either adenovirus or herpesvirus coinfection for their own replication.",
      "sentences": [
        [
          {
            "segment_text": "Members of the AAV subgroup ,",
            "crowd_label": "background"
          },
          {
            "segment_text": "now also known as the Dependoviruses ,",
            "crowd_label": "background"
          },
          {
            "segment_text": "are totally dependent upon either adenovirus or herpesvirus coinfection for their own replication .",
            "crowd_label": "background"
          }
        ]
      ]
    },
    {
      "original_text": "At present there is no published evidence of a member of this subgroup naturally infecting rodents. There is no a priori reason, however for believing that such defective agents do not exist, and investigators studying rodent adenovirus or herpesvirus infections ±n_ vivo or in cell culture should be aware of the potential problems that such contaminants would present.",
      "sentences": [
        [
          {
            "segment_text": "At present there is no published evidence of a member of this subgroup naturally infecting rodents .",
            "crowd_label": "background"
          }
        ],
        [
          {
            "segment_text": "There is no a priori reason ,",
            "crowd_label": "background"
          },
          {
            "segment_text": "however for believing that such defective agents do not exist ,",
            "crowd_label": "background"
          },
          {
            "segment_text": "and investigators studying rodent adenovirus or herpesvirus infections ± n _ vivo or in cell culture should be aware of the potential problems that such contaminants would present .",
            "crowd_label": "finding"
          }
        ]
      ]
    },
    {
      "original_text": "Viral and Mycoplasmal Infections",
      "sentences": [
        [
          {
            "segment_text": "Viral and Mycoplasmal Infections",
            "crowd_label": "finding"
          }
        ]
      ]
    }
  ],
  "abstract_stats": {
    "paragraph_num": "5",
    "sentence_num": "6",
    "segment_num": "11",
    "token_num": "139"
  }
}